qns/__init__.py
qns/__pycache__/__init__.cpython-38.pyc
qns/entity/__init__.py
qns/entity/entity.py
qns/entity/__pycache__/__init__.cpython-38.pyc
qns/entity/__pycache__/entity.cpython-38.pyc
qns/entity/cchannel/__init__.py
qns/entity/cchannel/cchannel.c
qns/entity/cchannel/cchannel.py
qns/entity/cchannel/__pycache__/__init__.cpython-38.pyc
qns/entity/cchannel/__pycache__/cchannel.cpython-38.pyc
qns/entity/memory/__init__.py
qns/entity/memory/event.py
qns/entity/memory/memory.c
qns/entity/memory/memory.py
qns/entity/memory/__pycache__/__init__.cpython-38.pyc
qns/entity/memory/__pycache__/memory.cpython-38.pyc
qns/entity/node/__init__.py
qns/entity/node/app.py
qns/entity/node/node.py
qns/entity/node/__pycache__/__init__.cpython-38.pyc
qns/entity/node/__pycache__/node.cpython-38.pyc
qns/entity/operator/__init__.py
qns/entity/operator/event.py
qns/entity/operator/operator.c
qns/entity/operator/operator.py
qns/entity/qchannel/__init__.py
qns/entity/qchannel/losschannel.c
qns/entity/qchannel/losschannel.py
qns/entity/qchannel/qchannel.c
qns/entity/qchannel/qchannel.py
qns/entity/qchannel/__pycache__/__init__.cpython-38.pyc
qns/entity/qchannel/__pycache__/qchannel.cpython-38.pyc
qns/entity/timer/__init__.py
qns/entity/timer/timer.py
qns/entity/timer/__pycache__/__init__.cpython-38.pyc
qns/entity/timer/__pycache__/timer.cpython-38.pyc
qns/models/__init__.py
qns/models/core/__init__.py
qns/models/core/backend.py
qns/models/epr/__init__.py
qns/models/epr/bell.c
qns/models/epr/bell.py
qns/models/epr/entanglement.c
qns/models/epr/entanglement.py
qns/models/epr/mixed.c
qns/models/epr/mixed.py
qns/models/epr/werner.c
qns/models/epr/werner.py
qns/models/qubit/__init__.py
qns/models/qubit/const.py
qns/models/qubit/decoherence.c
qns/models/qubit/decoherence.py
qns/models/qubit/errors.py
qns/models/qubit/factory.c
qns/models/qubit/factory.py
qns/models/qubit/gate.c
qns/models/qubit/gate.py
qns/models/qubit/qubit.c
qns/models/qubit/qubit.py
qns/models/qubit/utils.c
qns-0.1.4.dist-info/LICENSE
qns-0.1.4.dist-info/METADATA
qns-0.1.4.dist-info/WHEEL
qns-0.1.4.dist-info/top_level.txt
qns-0.1.4.dist-info/RECORD
