Metadata-Version: 2.1
Name: qns
Version: 0.1.4
Summary: A discrete-event scheduler designed for quantum networks
Home-page: https://github.com/ertuil/SimQN
Author: elliot
License: UNKNOWN
Platform: UNKNOWN
Classifier: Programming Language :: Python :: 3
Classifier: License :: OSI Approved :: GNU General Public License v3 (GPLv3)
Classifier: Operating System :: OS Independent
License-File: LICENSE
Requires-Dist: numpy
